ALU/src/alu_8bit.v
module alu_8bit(
    input [7:0] A,
    input [7:0] B,
    input [2:0] Sel,
    output reg [7:0] Result,
    output reg Carry
);

always @(*) begin
    Carry = 1'b0;

    case (Sel)

        // Addition
        3'b000:
            {Carry, Result} = A + B;

        // Subtraction
        3'b001:
            {Carry, Result} = A - B;

        // AND
        3'b010:
            Result = A & B;

        // OR
        3'b011:
            Result = A | B;

        // XOR
        3'b100:
            Result = A ^ B;

        // NOT
        3'b101:
            Result = ~A;

        // Left Shift
        3'b110:
            Result = A << 1;

        // Right Shift
        3'b111:
            Result = A >> 1;

        default: begin
            Result = 8'b00000000;
            Carry = 1'b0;
        end

    endcase
end

endmodule

ALU/tb/alu_8bit_tb.v
`timescale 1ns/1ps

module alu_8bit_tb;

reg [7:0] A;
reg [7:0] B;
reg [2:0] Sel;

wire [7:0] Result;
wire Carry;

alu_8bit uut (
    .A(A),
    .B(B),
    .Sel(Sel),
    .Result(Result),
    .Carry(Carry)
);

initial begin

    $dumpfile("dump.vcd");
    $dumpvars(0, alu_8bit_tb);

    $display("Time\tA\t\tB\t\tSel\tResult\t\tCarry");
    $monitor("%0t\t%b\t%b\t%b\t%b\t%b",
              $time, A, B, Sel, Result, Carry);

    // Addition
    A = 8'b00010101; B = 8'b00001010; Sel = 3'b000;
    #10;

    // Subtraction
    A = 8'b00010101; B = 8'b00000101; Sel = 3'b001;
    #10;

    // AND
    A = 8'b11001100; B = 8'b10101010; Sel = 3'b010;
    #10;

    // OR
    A = 8'b11001100; B = 8'b10101010; Sel = 3'b011;
    #10;

    // XOR
    A = 8'b11001100; B = 8'b10101010; Sel = 3'b100;
    #10;

    // NOT
    A = 8'b11001100; Sel = 3'b101;
    #10;

    // Left Shift
    A = 8'b00001111; Sel = 3'b110;
    #10;

    // Right Shift
    A = 8'b11110000; Sel = 3'b111;
    #10;

    // Addition with Carry
    A = 8'b11111111; B = 8'b00000001; Sel = 3'b000;
    #10;

    $finish;

end

endmodule

ALU/dump.vcd
$date
	Sun Jul 26 05:55:52 2026
$end
$version
	Icarus Verilog
$end
$timescale
	1ps
$end
$scope module alu_8bit_tb $end
$var wire 8 ! Result [7:0] $end
$var wire 1 " Carry $end
$var reg 8 # A [7:0] $end
$var reg 8 $ B [7:0] $end
$var reg 3 % Sel [2:0] $end
$scope module uut $end
$var wire 8 & A [7:0] $end
$var wire 8 ' B [7:0] $end
$var wire 3 ( Sel [2:0] $end
$var reg 1 " Carry $end
$var reg 8 ) Result [7:0] $end
$upscope $end
$upscope $end
$enddefinitions $end
$comment Show the parameter values. $end
$dumpall
$end
#0
$dumpvars
b11111 )
b0 (
b1010 '
b10101 &
b0 %
b1010 $
b10101 #
0"
b11111 !
$end
#10000
b10000 !
b10000 )
b1 %
b1 (
b101 $
b101 '
#20000
b10001000 !
b10001000 )
b10 %
b10 (
b10101010 $
b10101010 '
b11001100 #
b11001100 &
#30000
b11101110 !
b11101110 )
b11 %
b11 (
#40000
b1100110 !
b1100110 )
b100 %
b100 (
#50000
b110011 !
b110011 )
b101 %
b101 (
#60000
b11110 !
b11110 )
b110 %
b110 (
b1111 #
b1111 &
#70000
b1111000 !
b1111000 )
b111 %
b111 (
b11110000 #
b11110000 &
#80000
1"
b0 !
b0 )
b0 %
b0 (
b1 $
b1 '
b11111111 #
b11111111 &
