ALU/src/alu_16bit.v
module alu_16bit(
    input [15:0] A,
    input [15:0] B,
    input [2:0] Sel,
    output reg [15:0] Result,
    output reg Carry
);

always @(*) begin
    Carry = 1'b0;

    case (Sel)

        // Addition
        3'b000:
            {Carry, Result} = A + B;

        // Subtraction
        3'b001:
            {Carry, Result} = A - B;

        // AND
        3'b010:
            Result = A & B;

        // OR
        3'b011:
            Result = A | B;

        // XOR
        3'b100:
            Result = A ^ B;

        // NOT
        3'b101:
            Result = ~A;

        // Left Shift
        3'b110:
            Result = A << 1;

        // Right Shift
        3'b111:
            Result = A >> 1;

        default: begin
            Result = 16'b0000000000000000;
            Carry = 1'b0;
        end

    endcase
end

endmodule

ALU/tb/alu_16bit_tb.v
`timescale 1ns/1ps

module alu_16bit_tb;

reg [15:0] A;
reg [15:0] B;
reg [2:0] Sel;

wire [15:0] Result;
wire Carry;

alu_16bit uut (
    .A(A),
    .B(B),
    .Sel(Sel),
    .Result(Result),
    .Carry(Carry)
);

initial begin

    $dumpfile("dump.vcd");
    $dumpvars(0, alu_16bit_tb);

    $display("Time\tA\t\t\tB\t\t\tSel\tResult\t\t\tCarry");
    $monitor("%0t\t%h\t%h\t%b\t%h\t%b",
              $time, A, B, Sel, Result, Carry);

    // Addition
    A = 16'h0015; B = 16'h000A; Sel = 3'b000;
    #10;

    // Subtraction
    A = 16'h0015; B = 16'h0005; Sel = 3'b001;
    #10;

    // AND
    A = 16'hCCCC; B = 16'hAAAA; Sel = 3'b010;
    #10;

    // OR
    A = 16'hCCCC; B = 16'hAAAA; Sel = 3'b011;
    #10;

    // XOR
    A = 16'hCCCC; B = 16'hAAAA; Sel = 3'b100;
    #10;

    // NOT
    A = 16'hCCCC; Sel = 3'b101;
    #10;

    // Left Shift
    A = 16'h000F; Sel = 3'b110;
    #10;

    // Right Shift
    A = 16'hF000; Sel = 3'b111;
    #10;

    // Addition with Carry
    A = 16'hFFFF; B = 16'h0001; Sel = 3'b000;
    #10;

    $finish;

end

endmodule

ALU/dump.vcd
$date
	Sun Jul 26 06:06:13 2026
$end
$version
	Icarus Verilog
$end
$timescale
	1ps
$end
$scope module alu_16bit_tb $end
$var wire 16 ! Result [15:0] $end
$var wire 1 " Carry $end
$var reg 16 # A [15:0] $end
$var reg 16 $ B [15:0] $end
$var reg 3 % Sel [2:0] $end
$scope module uut $end
$var wire 16 & A [15:0] $end
$var wire 16 ' B [15:0] $end
$var wire 3 ( Sel [2:0] $end
$var reg 1 " Carry $end
$var reg 16 ) Result [15:0] $end
$upscope $end
$upscope $end
$enddefinitions $end
$comment Show the parameter values. $end
$dumpall
$end
#0
$dumpvars
b11111 )
b0 (
b1010 '
b10101 &
b0 %
b1010 $
b10101 #
0"
b11111 !
$end
#10000
b10000 !
b10000 )
b1 %
b1 (
b101 $
b101 '
#20000
b1000100010001000 !
b1000100010001000 )
b10 %
b10 (
b1010101010101010 $
b1010101010101010 '
b1100110011001100 #
b1100110011001100 &
#30000
b1110111011101110 !
b1110111011101110 )
b11 %
b11 (
#40000
b110011001100110 !
b110011001100110 )
b100 %
b100 (
#50000
b11001100110011 !
b11001100110011 )
b101 %
b101 (
#60000
b11110 !
b11110 )
b110 %
b110 (
b1111 #
b1111 &
#70000
b111100000000000 !
b111100000000000 )
b111 %
b111 (
b1111000000000000 #
b1111000000000000 &
#80000
1"
b0 !
b0 )
b0 %
b0 (
b1 $
b1 '
b1111111111111111 #
b1111111111111111 &
