ALU/src/alu_4bit.v
module alu(
    input  [3:0] A,
    input  [3:0] B,
    input  [2:0] Sel,
    output reg [3:0] Result,
    output reg Carry
);

always @(*) begin
    Carry = 0;

    case(Sel)

        3'b000: begin
            {Carry, Result} = A + B;
        end

        3'b001: begin
            {Carry, Result} = A - B;
        end

        3'b010: begin
            Result = A & B;
        end

        3'b011: begin
            Result = A | B;
        end

        3'b100: begin
            Result = A ^ B;
        end

        3'b101: begin
            Result = ~A;
        end

        3'b110: begin
            Result = A << 1;
        end

        3'b111: begin
            Result = A >> 1;
        end

        default: begin
            Result = 4'b0000;
            Carry = 0;
        end

    endcase
end

endmodule

ALU/tb/alu_tb.v
`timescale 1ns/1ps

module alu_tb;

    reg [3:0] A;
    reg [3:0] B;
    reg [2:0] Sel;

    wire [3:0] Result;
    wire Carry;

    alu uut(
        .A(A),
        .B(B),
        .Sel(Sel),
        .Result(Result),
        .Carry(Carry)
    );

    initial begin

        $dumpfile("dump.vcd");
        $dumpvars(0, alu_tb);

        $display("Time\tSel\tA\tB\tResult\tCarry");

        $monitor("%0t\t%b\t%b\t%b\t%b\t%b",
                  $time, Sel, A, B, Result, Carry);

        // Addition
        A = 4'b0101; B = 4'b0011; Sel = 3'b000; #10;

        // Subtraction
        A = 4'b1001; B = 4'b0010; Sel = 3'b001; #10;

        // AND
        A = 4'b1100; B = 4'b1010; Sel = 3'b010; #10;

        // OR
        A = 4'b1100; B = 4'b1010; Sel = 3'b011; #10;

        // XOR
        A = 4'b1100; B = 4'b1010; Sel = 3'b100; #10;

        // NOT
        A = 4'b1010; B = 4'b0000; Sel = 3'b101; #10;

        // Left Shift
        A = 4'b0011; B = 4'b0000; Sel = 3'b110; #10;

        // Right Shift
        A = 4'b1100; B = 4'b0000; Sel = 3'b111; #10;

        $finish;

    end

endmodule

ALU/dump.vcd
$date
	Sun Jul 26 04:44:49 2026
$end
$version
	Icarus Verilog
$end
$timescale
	1ps
$end
$scope module alu_tb $end
$var wire 4 ! Result [3:0] $end
$var wire 1 " Carry $end
$var reg 4 # A [3:0] $end
$var reg 4 $ B [3:0] $end
$var reg 3 % Sel [2:0] $end
$scope module uut $end
$var wire 4 & A [3:0] $end
$var wire 4 ' B [3:0] $end
$var wire 3 ( Sel [2:0] $end
$var reg 1 " Carry $end
$var reg 4 ) Result [3:0] $end
$upscope $end
$upscope $end
$enddefinitions $end
$comment Show the parameter values. $end
$dumpall
$end
#0
$dumpvars
b1000 )
b0 (
b11 '
b101 &
b0 %
b11 $
b101 #
0"
b1000 !
$end
#10000
b111 !
b111 )
b1 %
b1 (
b10 $
b10 '
b1001 #
b1001 &
#20000
b1000 !
b1000 )
b10 %
b10 (
b1010 $
b1010 '
b1100 #
b1100 &
#30000
b1110 !
b1110 )
b11 %
b11 (
#40000
b110 !
b110 )
b100 %
b100 (
#50000
b101 !
b101 )
b101 %
b101 (
b0 $
b0 '
b1010 #
b1010 &
#60000
b110 !
b110 )
b110 %
b110 (
b11 #
b11 &
#70000
b111 %
b111 (
b1100 #
b1100 &
